faster_eth_utils__mypyc.cpython-312-darwin.so
faster_eth_utils/debug.cpython-312-darwin.so
faster_eth_utils/network.cpython-312-darwin.so
faster_eth_utils/crypto.cpython-312-darwin.so
faster_eth_utils/hexadecimal.py
faster_eth_utils/address.py
faster_eth_utils/logging.py
faster_eth_utils/encoding.cpython-312-darwin.so
faster_eth_utils/numeric.cpython-312-darwin.so
faster_eth_utils/applicators.cpython-312-darwin.so
faster_eth_utils/applicators.py
faster_eth_utils/units.py
faster_eth_utils/encoding.py
faster_eth_utils/abi.cpython-312-darwin.so
faster_eth_utils/conversions.cpython-312-darwin.so
faster_eth_utils/functional.cpython-312-darwin.so
faster_eth_utils/conversions.py
faster_eth_utils/toolz.cpython-312-darwin.so
faster_eth_utils/decorators.cpython-312-darwin.so
faster_eth_utils/__init__.py
faster_eth_utils/units.cpython-312-darwin.so
faster_eth_utils/types.py
faster_eth_utils/humanize.py
faster_eth_utils/pydantic.py
faster_eth_utils/module_loading.cpython-312-darwin.so
faster_eth_utils/functional.py
faster_eth_utils/crypto.py
faster_eth_utils/debug.py
faster_eth_utils/humanize.cpython-312-darwin.so
faster_eth_utils/types.cpython-312-darwin.so
faster_eth_utils/numeric.py
faster_eth_utils/network.py
faster_eth_utils/py.typed
faster_eth_utils/abi.py
faster_eth_utils/exceptions.py
faster_eth_utils/currency.py
faster_eth_utils/module_loading.py
faster_eth_utils/__main__.py
faster_eth_utils/currency.cpython-312-darwin.so
faster_eth_utils/exceptions.cpython-312-darwin.so
faster_eth_utils/hexadecimal.cpython-312-darwin.so
faster_eth_utils/toolz.py
faster_eth_utils/address.cpython-312-darwin.so
faster_eth_utils/decorators.py
faster_eth_utils/curried/__init__.py
faster_eth_utils/typing/misc.py
faster_eth_utils/typing/__init__.py
faster_eth_utils/__json/eth_networks.json
faster_eth_utils-5.3.21.dist-info/RECORD
faster_eth_utils-5.3.21.dist-info/WHEEL
faster_eth_utils-5.3.21.dist-info/top_level.txt
faster_eth_utils-5.3.21.dist-info/METADATA
faster_eth_utils-5.3.21.dist-info/licenses/LICENSE
