Metadata-Version: 2.4
Name: faster-eth-utils
Version: 5.3.21
Summary: A faster fork of eth-utils: Common utility functions for python code that interacts with Ethereum. Implemented in C
Home-page: https://github.com/BobTheBuidler/faster-eth-utils
Author: The Ethereum Foundation
Author-email: snakecharmers@ethereum.org
License: MIT
Project-URL: Documentation, https://eth-utils.readthedocs.io/en/stable/
Project-URL: Release Notes, https://github.com/BobTheBuidler/faster-eth-utils/releases
Project-URL: Issues, https://github.com/BobTheBuidler/faster-eth-utils/issues
Project-URL: Source - Precompiled (.py), https://github.com/BobTheBuidler/faster-eth-utils/tree/master/faster_eth_utils
Project-URL: Source - Compiled (.c), https://github.com/BobTheBuidler/faster-eth-utils/tree/master/build
Project-URL: Benchmarks, https://github.com/BobTheBuidler/faster-eth-utils/tree/master/benchmarks
Project-URL: Benchmarks - Results, https://github.com/BobTheBuidler/faster-eth-utils/tree/master/benchmarks/results
Project-URL: Original, https://github.com/ethereum/eth-utils
Keywords: ethereum
Classifier: Intended Audience :: Developers
Classifier: Natural Language :: English
Classifier: Programming Language :: Python :: 3
Classifier: Programming Language :: Python :: 3.10
Classifier: Programming Language :: Python :: 3.11
Classifier: Programming Language :: Python :: 3.12
Classifier: Programming Language :: Python :: 3.13
Classifier: Programming Language :: Python :: 3.14
Classifier: Programming Language :: Python :: Implementation :: CPython
Requires-Python: >=3.10, <4
License-File: LICENSE
Requires-Dist: cchecksum==0.3.9
Requires-Dist: eth-hash>=0.3.1
Requires-Dist: eth-typing==5.2.1
Requires-Dist: eth-utils==5.3.1
Requires-Dist: toolz>0.8.2; implementation_name == "pypy"
Requires-Dist: cytoolz>=0.10.1; implementation_name == "cpython"
Requires-Dist: pydantic<3,>=2.0.0
Provides-Extra: dev
Requires-Dist: build>=0.9.0; extra == "dev"
Requires-Dist: bump_my_version>=0.19.0; extra == "dev"
Requires-Dist: eth-hash[pycryptodome]; extra == "dev"
Requires-Dist: ipython; extra == "dev"
Requires-Dist: mypy[mypyc]<1.20,>=1.14.1; extra == "dev"
Requires-Dist: pre-commit>=3.4.0; extra == "dev"
Requires-Dist: tox>=4.0.0; extra == "dev"
Requires-Dist: twine; extra == "dev"
Requires-Dist: wheel; extra == "dev"
Requires-Dist: sphinx>=6.0.0; extra == "dev"
Requires-Dist: sphinx-autobuild>=2021.3.14; extra == "dev"
Requires-Dist: sphinx_rtd_theme>=1.0.0; extra == "dev"
Requires-Dist: towncrier<26,>=24; extra == "dev"
Requires-Dist: hypothesis>=4.43.0; extra == "dev"
Requires-Dist: mypy[mypyc]<1.20,>=1.14.1; extra == "dev"
Requires-Dist: pytest-xdist>=2.4.0; extra == "dev"
Requires-Dist: pytest>=7.0.0; extra == "dev"
Provides-Extra: docs
Requires-Dist: sphinx>=6.0.0; extra == "docs"
Requires-Dist: sphinx-autobuild>=2021.3.14; extra == "docs"
Requires-Dist: sphinx_rtd_theme>=1.0.0; extra == "docs"
Requires-Dist: towncrier<26,>=24; extra == "docs"
Provides-Extra: test
Requires-Dist: hypothesis>=4.43.0; extra == "test"
Requires-Dist: mypy[mypyc]<1.20,>=1.14.1; extra == "test"
Requires-Dist: pytest-xdist>=2.4.0; extra == "test"
Requires-Dist: pytest>=7.0.0; extra == "test"
Provides-Extra: codspeed
Requires-Dist: pytest-codspeed<4.3,>=4.2; extra == "codspeed"
Requires-Dist: pytest-test-groups; extra == "codspeed"
Requires-Dist: pytest>=7.0.0; extra == "codspeed"
Provides-Extra: benchmark
Requires-Dist: eth-utils==5.3.1; extra == "benchmark"
Requires-Dist: pytest-benchmark<5.3,>=5.2; extra == "benchmark"
Requires-Dist: pytest-codspeed<4.3,>=4.2; extra == "benchmark"
Requires-Dist: pytest-test-groups; extra == "benchmark"
Requires-Dist: pytest>=7.0.0; extra == "benchmark"
Dynamic: author
Dynamic: author-email
Dynamic: classifier
Dynamic: description
Dynamic: description-content-type
Dynamic: home-page
Dynamic: keywords
Dynamic: license
Dynamic: license-file
Dynamic: project-url
Dynamic: provides-extra
Dynamic: requires-dist
Dynamic: requires-python
Dynamic: summary
